Metadata-Version: 1.1
Name: napalm-salt
Version: 0.0.2
Summary: NAPALM modules for Salt, to facilitate vendor-agnostic event-driven network automation and orchestration
Home-page: https://github.com/napalm-automation/napalm-salt
Author: Mircea Ulinic
Author-email: mircea.ulinic@gmail.com
License: Apache License 2.0
Keywords: napalm,salt,saltstack,network,automation
Platform: UNKNOWN
Classifier: Development Status :: 5 - Production/Stable
Classifier: Topic :: Utilities
Classifier: Topic :: System :: Networking
Classifier: Programming Language :: Python
Classifier: Programming Language :: Python :: 2
Classifier: Programming Language :: Python :: 2.7
Classifier: Programming Language :: Python :: 3
Classifier: Programming Language :: Python :: 3.4
Classifier: Programming Language :: Python :: 3.5
Classifier: Programming Language :: Python :: 3.6
Classifier: Operating System :: POSIX :: Linux
Classifier: Operating System :: POSIX :: Linux
Classifier: Operating System :: MacOS
Classifier: Intended Audience :: Developers
